nezu/__init__.py
nezu/_os_env.py
nezu/_parse.py
nezu/manual_tests/__init__.py
nezu/manual_tests/ztest_example.py
nezu/manual_tests/ztest_hide.py
nezu/manual_tests/ztest_nez.py
nezu/manual_tests/ztest_parsing.py
nezu/manual_tests/ztest_simple.py
nezu/nezu.json
nezu/nezu.py
nezu/parts/__init__.py
nezu/parts/cli.py
nezu/poetry.lock
nezu/tests/__init__.py
nezu/tests/test_class.py
nezu/tests/test_config.py
nezu/tests/test_line_checker.py
nezu/tests/test_say.py
nezu-0.5.1.dist-info/entry_points.txt
nezu-0.5.1.dist-info/LICENSE
nezu-0.5.1.dist-info/METADATA
nezu-0.5.1.dist-info/WHEEL
nezu-0.5.1.dist-info/RECORD
