Metadata-Version: 2.1
Name: nezu
Version: 0.5.1
Summary: Elegant debuging module
License: MIT
Author: Chuck Cartwright
Requires-Python: >=3.11,<4.0
Classifier: License :: OSI Approved :: MIT License
Classifier: Programming Language :: Python :: 3
Classifier: Programming Language :: Python :: 3.11
